{"slug":"07-254zip-5795","reference":"07_254.zip","gazette":"İst. Gümrük Mişavirleri Derneği,","title":"-","date":"01 Ocak 2007","bodyHtml":"<FONT face=sans-serif size=2>\n<P align=justify>Onaylanmış Kişi Statü Belgesi sahibi ve Sanayici olan Firmaların adlarına gelen kimyasal ürünler için taşıt üstü işleme müsaade edilmesi fakat bu işlem yapılırkenKimyagerlik Raporu'nun alınması, eşyanın fabrikaya boşaltılmasına nezaret edilmesi ve ithal aşamasında Jandarma veya Emniyet birimlerinin haberdar edilmesi suretiyle işlemlerin sonuçlandırılması hk.</P></FONT>\n                                <a target=\"_blank\" class=\"text-danger\" href=\"https://portal.ugm.com.tr/shared/DosyaAl.ashx?refno=REFSirkuler_07_254.zip&amp;arsivid=1f027628-0be5-4761-897d-4b1bab2f3aba\">\n                                    https://portal.ugm.com.tr/shared/DosyaAl.ashx?refno=REFSirkuler_07_254.zip&amp;arsivid=1f027628-0be5-4761-897d-4b1bab2f3aba\n                                </a>"}
