{"slug":"08-130zip-5650","reference":"08_130.zip","gazette":"27.05.2008 tarih 26888 sayılı Resmi Gazete,","title":"-","date":"01 Ocak 2008","bodyHtml":"<FONT face=Helv size=2>\n<P align=justify><FONT size=3>\"İthalatta Kota ve Tarife Kontenjanı İdaresi Hakkında Karar\" çerçevesinde, Gümrük Tarife İstatistik Pozisyonları (G.T.İ.P.) belirtilen Arnavutluk Cumhuriyeti menşeli tarım ürünleri için karşılarında gösterilen miktarlarda tarife kontenjanı açılması hk.</FONT></FONT><FONT face=\"Tms Rmn\"> </P></FONT>\n                                <a target=\"_blank\" class=\"text-danger\" href=\"https://portal.ugm.com.tr/shared/DosyaAl.ashx?refno=REFSirkuler_08_130.zip&amp;arsivid=55e3a360-a319-4811-ac11-c34e7e724825\">\n                                    https://portal.ugm.com.tr/shared/DosyaAl.ashx?refno=REFSirkuler_08_130.zip&amp;arsivid=55e3a360-a319-4811-ac11-c34e7e724825\n                                </a>"}
