{"slug":"sirkuler-20-398-7644","reference":"Sirkuler_20_398","gazette":"06 Mayıs 2020 Tarihli ve 31119 Sayılı Resmi Gazete","title":"Yetkilendirilmiş Yükümlülerin İzlenmesi Tebliğinin Yürürlükten Kaldırılmasına Dair Tebliğ","date":"06 Mayıs 2020","bodyHtml":"<p xss=removed>14/3/2017 tarihli ve 30007 sayılı Resmî Gazete’de yayımlanan Yetkilendirilmiş Yükümlülerin İzlenmesi Tebliği yürürlükten kaldırılmıştır.</p><p xss=removed>İlgili Tebliğ yetkilendirilmiş yükümlü sertifikasının verilmesine ilişkin koşullar ile sertifika kapsamı izin ve yetkilerin verilmesine ilişkin koşulların yetkilendirilmiş yükümlü sertifikası sahiplerince sağlanmaya devam edilip edilmediğinin bölge müdürlükleri bünyesindeki Ticaretin Kolaylaştırılması Şubelerince izlenmesine ilişkin usul ve esasları düzenlemekteydi.</p><p xss=removed>Gümrük İşlemlerinin Kolaylaştırılması Yönetmeliğinde Değişiklik Yapılmasına Dair Yönetmelik (21.02.2020 ile Tebliğ'in dayanağı olan 160. maddede yapılan değişiklikle  yapılacak yerinde izleme ve inceleme faaliyetlerinin GİKY 13 üncü maddede belirtilen yerinde inceleme usul ve esasları çerçevesinde gerçekleştirileceği düzenlenmişti.</p><p xss=removed><a  href=\"https://www.resmigazete.gov.tr/eskiler/2020/05/20200506-6.htm\">https://www.resmigazete.gov.tr/eskiler/2020/05/20200506-6.htm</a><br></p><p><br></p>\n                                <a target=\"_blank\" class=\"text-danger\" href=\"\">\n                                    \n                                </a>"}
