{"slug":"sirkuler-23-852-11312","reference":"Sirkuler_23_852","gazette":"Gümrükler Genel Müdürlüğü","title":"Firmaların e-ihracat beyanları konulu yazı yayımlandı","date":"28 Eylül 2023","bodyHtml":"<p>Gümrükler Genel Müdürlüğü \"Firmaların e-ihracat beyanları\"  konulu bir yazı yayımladı.</p><p>Yazıda Bakanlıkça gerçekleştirilen yurt dışı ziyaretlerde, yurt dışında zincir mağazaları bulunan çok kanallı (fiziksel/online satışı bulunan) markalarımızın satışlarının Kurumsal Kaynak Planlama (ERP) satış modülü üzerinden yapıldığı gözlemlenmiş olduğu belirtildi.</p><p>- E-ihracat Beyan Kılavuzunda da belirtildiği üzere, bayilik sistemi yurt dışı bağlantılı çok kanallı satış modeline veya çok uluslu şirketlerin farklı ülkeler üzerindeki dış ticaret işlemlerine (özellikle otomotiv ve beyaz eşya sektöründe) sahip firmaların, yurt dışı sipariş ve çıkışlarını ERP (Enterprise Resource Planning) üzerinden yapmaları durumunda 5178 kodlu “Bu ithalat/ihracat elektronik ticaret (e-ticaret) midir?” sorusuna “EVET” cevabının verilmesi ve Sipariş Türü Kodunu “1” olarak beyan edilmesi gerektiği, ayrıca; zincir mağazaların yurt dışında e-ticaret kanallarında gümrük beyannamesi yoluyla satışı varsa ve konsinye ihracat modeli ile satış gerçekleştiriliyorsa GB’de aynı şekilde 5178 kodlu soruya “EVET” cevabının verilmesi ancak sipariş kodu alanının 3 olarak işaretlenmesi ,</p><p>- yurtdışındaki e-ticaret kanallarına yönelik bu tür çıkışlar BGB' de muhakkak ET olarak beyan edilmesi gerektiği</p><p>belirtildi.</p><p><a  href=\"https://www.bugumder.org/dosya/26094224222698521793.pdf\" target=\"_blank\" xss=removed>Konuya ilişkin yazı için tıklayınız.</a></p><div><br></div>\n                                <a target=\"_blank\" class=\"text-danger\" href=\"\">\n                                    \n                                </a>"}
