{"slug":"sirkuler-18-466-691","reference":"Sirkuler_18_466","gazette":"15.08.2018 Resmi Gazete Mükerrer","title":"Tereftalik asit damping soruşturmasının önlemsiz kapatılması","date":"15 Ağustos 2018","bodyHtml":"<p style=\"text-align: justify; \">Kore Cumhuriyeti, İspanya Krallığı ve Belçika Krallığı menşeli 2917.36.00.00.11 gümrük tarife istatistik pozisyonunda sınıflandırılan “tereftalik asit” ithalatına yönelik başlatılan ve T.C. Ticaret Bakanlığı İthalat Genel Müdürlüğü tarafından yürütülen damping soruşturması kapsamında yerli üretim dalı tarafından yapılan damping soruşturması başvurusunun soruşturma süresi içerisinde geri çekilmesi neticesinde soruşturmanın önlemsiz olarak kapatılmasına karar verilmiştir.</p><p style=\"text-align: justify; \">2018/27 sayılı tebliğ eklidir.<br></p>\n                                <a target=\"_blank\" class=\"text-danger\" href=\"https://portal.ugm.com.tr/shared/DosyaAl.ashx?refno=REF2018_466.rar&amp;arsivid=9945d8fa-bb59-45e0-acaf-28392f50adf8\">\n                                    https://portal.ugm.com.tr/shared/DosyaAl.ashx?refno=REF2018_466.rar&amp;arsivid=9945d8fa-bb59-45e0-acaf-28392f50adf8\n                                </a>"}
