{"slug":"sirkuler-19-612-6374","reference":"Sirkuler_19_612","gazette":"Official Journal of the European Union, L 248, 27 September 2019","title":"AB Çelik ürünlerinde korunma önleminde değişikliklere gitti","date":"27 Eylül 2019","bodyHtml":"<p>AB 2019 Şubat ayından itibaren çelik ürünlerine uyguladığı %25 ilave gümrük vergisine ilişkin olarak bazı değişiklikler yaptı. Türkiye ile ilgili değişiklikler;</p><p>-7219 21 10, 7219 21 90&nbsp; tarife pozisyonlarında Türkiye ilave gümrük vergisinden muaf tutuldu.</p><p>-7304 19 10, 7304 19 30, 7304 19 90, 7304 23 00, 7304 29 10, 7304 29 30, 7304 29 90, 7304 31 20, 7304 31 80,</p><p>7304 39 10, 7304 39 52, 7304 39 58, 7304 39 92, 7304 39 93, 7304 39 98, 7304 51 81, 7304 51 89, 7304 59 10,</p><p>7304 59 92, 7304 59 93, 7304 59 99, 7304 90 00 tarife pozisyonları için Türkiye ilave gümrük vergisi uygulanacak ülkeler arasında alındı.</p><p><br></p><p>Yeni uygulama 1 Ekim 2019'da yürürlüğe girecek.</p><p>İlgili değişiklik metni;</p><p><a  href=\"https://eur-lex.europa.eu/legal-content/EN/TXT/?uri=uriserv:OJ.L_.2019.248.01.0028.01.ENG&amp;toc=OJ:L:2019:248:TOC\">https://eur-lex.europa.eu/legal-content/EN/TXT/?uri=uriserv:OJ.L_.2019.248.01.0028.01.ENG&amp;toc=OJ:L:2019:248:TOC</a><br></p><p><br></p>\n                                <a target=\"_blank\" class=\"text-danger\" href=\"\">\n                                    \n                                </a>"}
