{"slug":"sirkuler-15-309-2774","reference":"Sirkuler_15_309","gazette":"İ.G.M.D","title":"Ticaret Politikasi Onlemlerine Tabi Esyada Mense Sahadetnamesi Ibrazi hk.","date":"25 Mayıs 2015","bodyHtml":"<p style=\"text-align: justify;\">\n\t<span style=\"color:#0000cd;\"><strong><u><span style=\"color:#f00;\">Avrupa Birliği &uuml;lkelerinden A.TR dolaşım Belgesi kapsamında gelen ve Anti-Damping vergisi, ilave g&uuml;mr&uuml;k vergisi ve /veya ek mali y&uuml;k&uuml;ml&uuml;ğe tabi olan</span></u> <u>54.07, 55.13, 55.14, 55.15, 55.16, 58.10, 61.01, 61.04, 61.05, 61.06 G&uuml;mr&uuml;k Tarife Pozisyonlarında yer alan kumaş/mensucat cinsi eşyaların ithalinde menşei ispat belgesinin aranmasının zorunlu hale getirilmesi gerektiği</u>, <u><span style=\"background-color:#ffff00;\">bu t&uuml;r eşyaların ithalinde Menşe Şahadetnamesi aranması gerektiği </span></u></strong></span>hk.</p>\n\n                                <a target=\"_blank\" class=\"text-danger\" href=\"https://portal.ugm.com.tr/shared/DosyaAl.ashx?refno=REFsirkuler_15_309.zip&amp;arsivid=537f329e-9f3d-48d8-8d40-61aa850cea39\">\n                                    https://portal.ugm.com.tr/shared/DosyaAl.ashx?refno=REFsirkuler_15_309.zip&amp;arsivid=537f329e-9f3d-48d8-8d40-61aa850cea39\n                                </a>"}
