{"slug":"sirkuler-12-273-4437","reference":"Sirkuler_12_273","gazette":"Risk Yönetimi ve Kontrol Genel Müdürlüğü","title":"Ozel Tuketim Vergisi Goturu Teminat hk.","date":"10 Eylül 2012","bodyHtml":"<p>\n\t&Ouml;zel T&uuml;ketim Vergisi Kanunu&#39;nun <span style=\"color: #00f\"><strong>Eki (I) sayılı Listenin (B) cetveli</strong></span>nde yer alan malların ithali durumunda <span style=\"color: #00f\"><strong>G&ouml;t&uuml;r&uuml; Teminat </strong></span>sisteminden yararlanılmasının <span style=\"color: #f00\"><u><strong>m&uuml;mk&uuml;n olmadığı </strong></u></span>hk.</p>\n\n                                <a target=\"_blank\" class=\"text-danger\" href=\"https://portal.ugm.com.tr/shared/DosyaAl.ashx?refno=REFsirkuler_12_273.rar&amp;arsivid=964be7d2-a4e5-4b1e-88cc-2b40335cb5d2\">\n                                    https://portal.ugm.com.tr/shared/DosyaAl.ashx?refno=REFsirkuler_12_273.rar&amp;arsivid=964be7d2-a4e5-4b1e-88cc-2b40335cb5d2\n                                </a>"}
