{"slug":"sirkuler-20-116-7350","reference":"Sirkuler_20_116","gazette":"Gümrükler Genel Müdürlüğü","title":"Asfaltın 2011-2033 Sayılı Karar Kapsamına alınması hk.","date":"28 Şubat 2020","bodyHtml":"<p xss=removed>2011/2033 sayılı Ham Petrol ve Bazı Petrol Ürünlerinin Karayolu veya Demiryolu ile İthali, İhracı ve Transitine İlişkin Karar’da 20.02.2020 tarihli ve 31045 sayılı Resmi Gazetede yayımlanan 2120 sayılı Karar ile değişiklik yapılarak 2713.20 tarife alt pozisyonunda yer alan asfaltın karayolu ve demiryoluyla ithali, ihracı ve transiti de mezkur Karar kapsamına alınmış olup söz konusu Kararın yayımı tarihi itibarıyla Ticaret Bakanlığı 2713.20 tarife alt pozisyonunda yer alan asfaltın karayolu ve demiryoluyla ithali, ihracı ve transitine izin vermeye yetkili kılınmıştır.</p><p xss=removed>Kararın yayımı tarihinden önce taşıma belgesi düzenlenerek yüklemesi yapılmış olan anılan eşyanın gerek sınır gümrük idarelerinde gerekse iç gümrük idarelerinde gümrük işlemlerine devam edilecektir.</p><p xss=removed>Konuya ilişkin yazı eklidir.</p>\n                                <a target=\"_blank\" class=\"text-danger\" href=\"http://portal.ugm.com.tr/shared/dosyaal.ashx?arsivid=1d7264f9-672d-43dd-baea-f952c15529d2&amp;refno=REF2020_116.rar\">\n                                    http://portal.ugm.com.tr/shared/dosyaal.ashx?arsivid=1d7264f9-672d-43dd-baea-f952c15529d2&amp;refno=REF2020_116.rar\n                                </a>"}
