{"slug":"sirkuler-22-411-9728","reference":"Sirkuler_22_411","gazette":"Ticaret Araştırmaları ve Risk Değerlendirme Genel Müdürlüğü","title":"Azerbaycan’da İthalatı Ve Satışı KDV’den Muaf Tutulan Matbaa Ürünleri ve kitapların Listesi Onaylandı","date":"17 Mayıs 2022","bodyHtml":"<p xss=removed>Azerbaycan Cumhuriyeti Bakanlar Kurulunun 13 Mayıs 2022 tarih ve 184 sayılı Kararı (<a  href=\"https://nk.gov.az/az/document/6120\" target=\"_blank\" xss=removed>https://nk.gov.az/az/document/6120</a>/) ile, ithalatı ve satışı KDV’den muaf tutulan matbaa ürünleri ve kitapların (e-kitaplar hariç), aynı zamanda ders kitapları ve söz konusu ürünlerin baskısı ile ilgili rulo veya yaprak şeklindeki kağıtların listesi onaylandı.</p><p>Listeye aşağıdaki ürünler dahildir:</p><p>-Rulo veya tabaka halinde gazete kağıdı;</p><p>-Yazı, baskı veya diğer grafik amaçlı kullanılan çeşitli ebat ve gramlarda tebeşir olmayan kağıt ve karton;</p><p>-Ciltleme için kağıt ve karton kapak;</p><p>-Resimli veya resimsiz, reklam malzemesi olan veya olmayan gazeteler, dergiler ve diğer süreli yayınlar;</p><p>-Kitaplar-resimler, çizim veya boyama için çocuk kitapları;</p><p>-Kitap şeklinde basılmış atlaslar, duvar haritaları, topografik planlar dahil coğrafi ve hidrografik haritalar veya her türlü benzer haritalar.</p>\n                                <a target=\"_blank\" class=\"text-danger\" href=\"\">\n                                    \n                                </a>"}
