{"slug":"sirkuler-21-738-9148","reference":"Sirkuler_21_738","gazette":"06 Kasım 2021 Tarihli ve 31651 Sayılı Resmî Gazete","title":"Türkiye İhracatçılar Meclisi ile İhracatçı Birliklerinin Kuruluş ve Görevleri Hakkında Kanun ile Bazı Kanunlarda Değişiklik Yapılamasına Dair Kanun","date":"06 Kasım 2021","bodyHtml":"<p xss=removed>7341 Türkiye İhracatçılar Meclisi ile İhracatçı Birliklerinin Kuruluş ve Görevleri Hakkında Kanun ile Bazı Kanunlarda Değişiklik Yapılmasına Dair Kanun Resmi Gazete'de yayımlanarak yürürlüğe girdi.</p><p xss=removed>İhracatı Geliştirme AŞ'ye aktarılmak üzere, ihracat işlemleri üzerinden FOB bedelin on binde üçüne kadar  Ticaret Bakanlığı'nca belirlenecek oranda ek nispi ödeme kesintisi yapılacak. Ayrıca Hizmet sektörleri için İhracatı Geliştirme Anonim Şirketinin sermayesine eklenmek üzere, on altı yaşından büyükler için uygulanan aylık asgarî ücretin on katına kadar Ticaret Bakanlığınca yıllık cirolara göre belirlenen tutarda ilave yıllık aidat tahsil edilecek.</p><p xss=removed>Serbest Bölgeler Kanununa eklenen ek maddeye (EkMadde4) istinaden  ilk kez faaliyete geçecek serbest bölgelerde, işleticilerin serbest bölgelerin işletilmesi ile ilgili faaliyetlerden elde ettikleri kazançları, 30 yılı geçmemek ve Ticaret Bakanlığınca kendilerine verilecek ilk faaliyet ruhsatında belirtilen süre ile sınırlı olmak üzere gelir veya kurumlar vergisinden müstesna olacak.</p><p xss=removed><br></p><p> </p>\n                                <a target=\"_blank\" class=\"text-danger\" href=\"\">\n                                    \n                                </a>"}
