{"slug":"sirkuler-13-237-4062","reference":"Sirkuler_13_237","gazette":"01.07.2013 tarih 28694 sayılı Resmi Gazete","title":"Ithalat Rejimi Kararina Ek Karar (2013-4972) (V sayili Liste) hk.","date":"01 Temmuz 2013","bodyHtml":"<p>\n\t<span style=\"color: rgb(0, 0, 205);\"><strong>EK:II sayılı listede G&uuml;mr&uuml;k Tarife istatistik Pozisyonları (G.T.İ.P) ve kayıt numaraları belirtilen &uuml;r&uuml;nlerin, 95/7606 sayılı Bakanlar Kurulu Kararı ile y&uuml;r&uuml;rl&uuml;ğe konulan İthalat Rejimi Kararının eki V sayılı listeden &ccedil;ıkartıldığı ve EK:I sayılı listede G&uuml;mr&uuml;k Tarife istatistik Pozisyonları (G.T.İ.P), kayıt numaraları, madde isimleri ve g&uuml;mr&uuml;k vergisi oranları belirtilen &uuml;r&uuml;nlerin, İthalat Rejimi Kararının eki V sayılı listeye ilave edildiği ile bu Karar&#39;ın 0<u>1/07/2013 tarihinden ge&ccedil;erli olmak &uuml;zere yayımı tarihinde y&uuml;r&uuml;rl&uuml;ğe girdiği </u></strong></span>hk.</p>\n\n                                <a target=\"_blank\" class=\"text-danger\" href=\"https://portal.ugm.com.tr/shared/DosyaAl.ashx?refno=REFsirkuler_13_237.rar&amp;arsivid=a9b843b0-949b-4c6f-a3dd-4baa84114f4b\">\n                                    https://portal.ugm.com.tr/shared/DosyaAl.ashx?refno=REFsirkuler_13_237.rar&amp;arsivid=a9b843b0-949b-4c6f-a3dd-4baa84114f4b\n                                </a>"}
