{"slug":"sirkuler-22-312-9623","reference":"Sirkuler_22_312","gazette":"20 Nisan 2022 Tarihli ve 31815 Sayılı Resmî Gazete","title":"Kara nakil vasıtalarında kullanılan türden oturmaya mahsus mobilyaların aksamlarında ilave gümrük vergisi uygulamasında değişiklik yapıldı (9401.99.90.00.00 GTİP)","date":"20 Nisan 2022","bodyHtml":"<p xss=removed>9401.99.90.00.00 GTİP'te sınıflandırılan ve yüzde 15 ilave gümrük vergisi (İGV) uygulanan mobilya aksamlarının  ilave gümrük vergisi uygulamasında değişikliğe gidildi. </p><p xss=removed>İlave Gümrük Vergisi Kararı'nın ilgili satırına eklenen 9 nolu dipnota göre ilgili GTİP'teki eşyayı <span xss=removed>kara nakil vasıtalarında kullanılan türden oturmaya mahsus mobilyaların üretiminde girdi olarak kullanan</span> firmalarca yapılan ithalatta İGV yüzde 0  olarak uygulanacak. Bu durumda nihai kullanım hükümleri geçerli olacak.</p><p>Değişikliği yapan  5444  sayılı Karar için <a  href=\"https://www.resmigazete.gov.tr/eskiler/2022/04/20220420-6.pdf\" target=\"_blank\" xss=removed>tıklayınız.</a></p>\n                                <a target=\"_blank\" class=\"text-danger\" href=\"\">\n                                    \n                                </a>"}
