{"slug":"sirkuler-21-540-8930","reference":"Sirkuler_21_540","gazette":"30 Temmuz 2021 Tarihli ve 31553 Sayılı Resmî Gazete","title":"İthalatta Kota ve Tarife Kontenjanı İdaresine İlişkin Tebliğ (No: 2021/6)","date":"30 Temmuz 2021","bodyHtml":"<p>4814.20.00.00.00, 4814.90.10.00.00 ve 4814.90.70.10.00 gümrük tarife istatistik pozisyonunda yer alan eşyanın ithalatında 9/7/2021 tarihli ve 4247 sayılı Cumhurbaşkanı Kararı ile yürürlüğe konulan Duvar Kâğıdı ve Benzeri Duvar Kaplamaları İthalatında Korunma Önlemi Uygulanmasına İlişkin Karar kapsamında, ek mali yükümlülük şeklinde uygulanan korunma önleminden muafiyet sağlanması için açılan tarife kontenjanının kullanım usul ve esaslarını düzenleyen   <a  href=\"https://www.resmigazete.gov.tr/eskiler/2021/07/20210730-8.htm\" target=\"_blank\" xss=removed>İthalatta Kota ve Tarife Kontenjanı İdaresine İlişkin Tebliğ (No: 2021/6)</a> yayımlandı.</p><p>Tarife kontenjanı miktarı, ek mali yükümlülüğün uygulandığı her bir dönem için, 4247 sayılı Cumhurbaşkanı Kararı ekinde yer alan ülkeler ve gümrük bölgeleri menşeli tarife kontenjanı kapsamı eşyanın tamamı için toplam 1.043 ton olarak belirlenmiştir. Her bir ülke veya gümrük bölgesi menşeli eşya için bir dönemde verilecek tarife kontenjanı 347 tonu geçemez.</p><p>Tarife kontenjanı taleplerine ilişkin başvurular, Ticaret Bakanlığı (Bakanlık) internet sitesinde (www.ticaret.gov.tr) yer alan E-İmza Uygulamaları altındaki “E-imza Uygulamalarına Giriş” bölümünde bulunan “İthalat İşlemleri” kısmında elektronik imza ile yapılacak.</p><p>Tarife kontenjanı kapsamında yapılacak ithalatta Bakanlıkça düzenlenen ithal lisansı gümrük beyannamesinin tescilinde ilgili gümrük idaresince aranacak.</p><p><br></p><p><br></p><p><br></p>\n                                <a target=\"_blank\" class=\"text-danger\" href=\"\">\n                                    \n                                </a>"}
