{"slug":"sirkuler-22-254-9559","reference":"Sirkuler_22_254","gazette":"Sirkuler_22_254","title":"Transit rejiminde memur refakati talepleri Bölge Müdürlüklerince sonuçlandırılacak (2022/6 sayılı Genelge)","date":"04 Nisan 2022","bodyHtml":"<p>Gümrükler Genel Müdürlüğü'nün \"Transit Rejimi ile ilgili işlemler\" konulu 2012/4 sayılı Genelgesinde değişiklik yapıldı.</p><p>Yapılan değişiklikle  Genelge'de sayılan durumlar haricinde transit beyannamesi kapsamı eşyaya memur refakati uygulanmasını gerektirecek bir durumun ortaya çıkması durumunda  talepler ilgili Bölge Müdürlüğünce sonuçlandırılacak. Değişiklik öncesinde bu tür talepler Bakanlığa bildirilmekte  ve gelen talimata göre işlem yapılmaktaydı.</p><p>Değişikliği yapan 2022/6 sayılı Genelge için<a  href=\"https://ticaret.gov.tr/data/61d2b98e13b8761d788ed370/2022-6%20Say%C4%B1l%C4%B1%20Genelge%20(2012_4%20Say%C4%B1l%C4%B1%20Genelgede%20De%C4%9Fi%C5%9Fiklik)_Ek_2022-6%20say%C4%B1l%C4%B1%20Genelge(2012-4%20say%C4%B1l%C4%B1%20Genelgede%20De%C4%9Fi%C5%9Fiklik).pdf\" target=\"_blank\" xss=removed> tıklayınız.</a></p><p>Değişikliğe konu ilgili madde:</p><p><span xss=removed>7- Transit rejiminde memur refakati</span></p><p xss=removed>(1) Gümrük Yönetmeliğinin 229 uncu maddesi hükümleri saklı kalmak kaydıyla ve aynı Yönetmeliğin 249 uncu maddesinin 2 nci fıkrası uyarınca aşağıda sayılan istisnai haller dışında transit beyannamesi kapsamı eşya varış gümrüğüne her durumda teminatlı olarak, memur refakati olmaksızın ve herhangi bir üst yazıya bağlanmaksızın sevk edilir, sevk edilen transit beyannamelerinin teyitleri titizlikle takip edilir.<br></p><p xss=removed>a) İthali yasak eşyanın transit beyannamesi ile sevki mutlak surette teminatlı ve memur refakatli olarak yapılır.<br></p><p xss=removed>b) Aşağıdaki durumlarda, eşyanın transit beyannamesi kapsamında varış gümrük idaresine sevkinde yükümlüsünce teminat verilemediği ve yazılı talepte bulunulduğu hallerde gümrük idaresinin imkanları dahilinde memur refakati uygulanır:<br></p><p xss=removed>i) Sürülerek götürülen taşıtlar (taşıtın kendisinin eşya olduğu durumlar),<br></p><p xss=removed>ii) Özel kullanıma mahsus taşıtlarda bulunan eşya,<br></p><p xss=removed>iii) Aynı Bölge Müdürlüğüne bağlı ve aynı belediye sınırları içerisinde yer alan gümrük idareleri arasında taşınacak eşya,<br></p><p xss=removed>iv) Serbest bölgelerden çıkarılarak yurtdışı edilecek olan Türk menşeli eşya.<br></p><p><span xss=removed><span xss=removed>ESKİ: </span>c) (a) ve (b) fıkralarında sayılan durumlar haricinde transit beyannamesi kapsamı eşyaya memur refakati uygulanmasını gerektirecek bir durumun ortaya çıkması halinde talep gerekçesiyle birlikte ilgili Bölge Müdürlüğünce Bakanlığa bildirilir ve alınacak talimata göre işlem yapılır.</span></p><p><span xss=removed>YENİ:</span> c)(a) ve (b) fıkralarında sayılan durumlar haricinde transit beyannamesi kapsamı eşyaya memur refakati uygulanmasını gerektirecek bir durumun ortaya çıkması halinde talep, gerekçesiyle birlikte ilgili Bölge Müdürlüğüne bildirilir ve Bölge Müdürü tarafından değerlendirilerek sonuçlandırılır.</p><p><br></p><div><br></div>\n                                <a target=\"_blank\" class=\"text-danger\" href=\"\">\n                                    \n                                </a>"}
