{"slug":"sirkuler-22-878-10222","reference":"Sirkuler_22_878","gazette":"Türkiye İlaç ve Tıbbi Cihaz Kurumu","title":"Pregabalin içeren ilaçlar için yeni düzenleme yapıldı","date":"02 Aralık 2022","bodyHtml":"<p>Türkiye İlaç ve Tıbbi Cihaz Kurumu \" Pregabalin İçeren İlaçlar İçin Yapılan Düzenleme Hk\" başlıklı bir yazı yayımladı.</p><p>Halihazırda pregabalin içeren ilaçlar için edinilen ve geçerlilik süresi 6 ay olan miktar düşümlü uyuşturucu veya psikotrop madde ihtiva etmediğine dair gümrükleri bilgilendirme yazılarının 13.05.2023 tarihine kadar geçerli olduğu, 14.11.2022 tarihinden itibaren ise pregabalin içeren ilaçlar için söz konusu bilgilendirme yazısının düzenlenmeyeceği  söz konusu ilaçların ihracatında Kurumca yalnızca firmaların ihracat permisi başvurularının değerlendirmeye alınacağı belirtildi.</p><p>İlgili yazı eklidir.</p><p><br></p>\n                                <a target=\"_blank\" class=\"text-danger\" href=\"http://portal.ugm.com.tr/shared/dosyaal.ashx?arsivid=53089619-03ef-41ce-b6bb-9a062e74cf9e&amp;refno=REF2022_878.rar\">\n                                    http://portal.ugm.com.tr/shared/dosyaal.ashx?arsivid=53089619-03ef-41ce-b6bb-9a062e74cf9e&amp;refno=REF2022_878.rar\n                                </a>"}
