{"slug":"sirkuler-12-132-4581","reference":"Sirkuler_12_132","gazette":"05.06.2012 Tarihli, 28314 Sayılı Resmi Gazete,","title":"Ham petrol ve jet yakıtı Transiti konulu Gümrük Genel Tebliği (Transit) (Seri No:2) hk.","date":"05 Haziran 2012","bodyHtml":"<p style=\"text-align: justify;\">\n\t&Uuml;lke menfaati a&ccedil;ısından gerekli olan hallerde, transitine izin verilen ham petrol ve jet yakıtının T&uuml;rkiye Cumhuriyeti G&uuml;mr&uuml;k B&ouml;lgesinde karayolu veya demiryolu ile transitinde uyulacak usul ve esaslar hk.<br />\n\t&nbsp;</p>\n\n                                <a target=\"_blank\" class=\"text-danger\" href=\"https://portal.ugm.com.tr/shared/DosyaAl.ashx?refno=REFsirkuler_12_06051238.zip&amp;arsivid=f736ba16-965a-4ed3-afda-22f632022060\">\n                                    https://portal.ugm.com.tr/shared/DosyaAl.ashx?refno=REFsirkuler_12_06051238.zip&amp;arsivid=f736ba16-965a-4ed3-afda-22f632022060\n                                </a>"}
