{"slug":"sirkuler-19-660-6955","reference":"Sirkuler_19_660","gazette":"19 Ekim 2019 Tarihli ve 30923 Sayılı Resmi Gazete","title":"Vergi Usul Kanunu Genel Tebliği (Sıra No:456)’nde Değişiklik Yapılmasına Dair Tebliğ (Sıra No:511)","date":"22 Ekim 2019","bodyHtml":"<p xss=removed>Vergi Usul Kanunu Genel Tebliği (Sıra No: 456)’nde Değişiklik Yapılmasına Dair Tebliğ (Sıra No:511) ile yapılan düzenlemeler sonucunda, vergi dairesi müdürlüklerinin yanı sıra Gelir İdaresi Başkanlığının merkez ve taşra birimlerinin tamamı ile Vergi Denetim Kurulu Başkanlığı da 213 sayılı Kanun kapsamında hazırladıkları belgeleri Gelir İdaresi Başkanlığı aracılığıyla elektronik ortamda tebliğ edebilecektir.</p><p xss=removed>Ayrıca yapılan düzenleme ile malmüdürlüklerine bağlı kurumlar vergisi mükellefleri ile ticari, zirai ve mesleki kazanç yönünden gelir vergisi mükellefiyeti bulunanlar (Kazançları basit usulde tespit edilenlerle gerçek usulde vergiye tabi olmayan çiftçiler hariç) elektronik tebligat sistemi kapsamına alınmışlardır.</p><p xss=removed>Elektronik tebligat sistemi kapsamına alınan malmüdürlüğüne bağlı  mükelleflerden 456 sıra nolu Vergi Usul Kanunun Genel Tebliğinde belirtilen zorunluluk kapsamına giren gelir vergisi mükelleflerinin bağlı oldukları malmüdürlüğüne ya da İnteraktif Vergi Dairesi üzerinden elektronik ortamda; kurumlar vergisi mükelleflerinin ise bağlı oldukları malmüdürlüğüne  31.12.2019 tarihine kadar Tebliğ ekinde yer alan Elektronik Tebligat Talep Bildirimi ile başvuruda bulunmaları  gerekmektedir.</p><p xss=removed>Gerçek kişilerde muhatabın; tüzel kişilerde ise şirketin tek kanuni temsilcisi olması durumunda ilgili kanuni temsilcinin, birden çok kanuni temsilcisi olması durumunda tüm kanuni temsilcilerin görme engelli olduklarının ispat ve tevsik edilmesi durumunda, bu mükelleflere elektronik tebligat sistemi kullanılmadan Kanunun 93 ve müteakip maddelerinde belirtilen diğer tebliğ usullerine göre tebligat işlemi yapılacağına ilişkin düzenleme yapılmıştır.</p><p xss=removed>İlgili Tebliğ için;</p><p xss=removed><a  href=\"https://www.resmigazete.gov.tr/eskiler/2019/10/20191019-7.htm\">https://www.resmigazete.gov.tr/eskiler/2019/10/20191019-7.htm</a><br></p>\n                                <a target=\"_blank\" class=\"text-danger\" href=\"\">\n                                    \n                                </a>"}
