{"slug":"sirkuler-15-342-2738","reference":"Sirkuler_15_342","gazette":"T.C. Gümrük ve Ticaret Bakanlığı","title":"Tasfiyelik hale gelen oyuncak cinsi esyalarin analizleri hk.","date":"15 Haziran 2015","bodyHtml":"<p style=\"text-align: justify;\">\n\t<span style=\"color:#f00;\"><strong><span style=\"color:#0000cd;\"><u>&#39;&#39;CE&#39;&#39; işareti bulunmayan oyuncakların yeniden ihra&ccedil; amacıyla satış veya imha suretiyle tasfiye edilmesi,</u></span> <u>&uuml;zerinde &#39;&#39;CE&#39;&#39; işareti bulunan oyuncakların tasfiyesinde ise</u> gerekli analizlerin, oyuncakların piyasa g&ouml;zetimi ve denetiminin, T&uuml;keticinin Korunması ve Piyasa G&ouml;zetimi Genel M&uuml;d&uuml;rl&uuml;ğ&uuml;&#39;nce belirlenmiş laboratuvarlarda yaptırılması, ilgili laboratuvarlardan &ouml;ncelikle eşyanın fiziksel/mekanik testlerinin yapılmasının, bu<u> test sonu&ccedil;ları olumlu olanların kimyasal testlere tabi tutularak sonu&ccedil;larının bildirilmesinin istenilmesi gerektiğ</u>i</strong></span> hk.</p>\n\n                                <a target=\"_blank\" class=\"text-danger\" href=\"https://portal.ugm.com.tr/shared/DosyaAl.ashx?refno=REFsirkuler_15_342.zip&amp;arsivid=ad18a6a4-b6fc-43d4-9a20-33c03857e89e\">\n                                    https://portal.ugm.com.tr/shared/DosyaAl.ashx?refno=REFsirkuler_15_342.zip&amp;arsivid=ad18a6a4-b6fc-43d4-9a20-33c03857e89e\n                                </a>"}
