{"slug":"sirkuler-20-260-7499","reference":"Sirkuler_20_260","gazette":"03 Nisan 2020 Tarihli ve 31088 Sayılı Resmi Gazete","title":"KOBİ’ler için Yatırım ve İşletme Kredi Üst Limitinin Güncellenmesi Hakkında","date":"03 Nisan 2020","bodyHtml":"<p>03.04.2020 tarih ve 31088 sayılı Resmi Gazete’de yayımlanan  Küçük ve Orta Ölçekli Sanayi İşletmelerinin Geliştirilmesi ve Desteklenmesi Amacıyla KOSGEB Tarafından Uygun Koşullarda Finansal Destek Sağlanması Hakkında Kararda Değişiklik Yapılmasına Dair Karar (Karar Sayısı : 2350) ile;</p><p>- Yatırım ve işletme kredi üst limiti KOBİ başına 300.000 TL’de 3 milyon TL’ye çıkarılmış,</p><p>- Kredilerin vadesi 48 aydan 60 aya uzatılmıştır.</p><p>KOBİ'lere sağlanacak finansman desteğine ilişkin başvuru, değerlendirme ve destekten faydalanma koşulları ile iş ve işlem akışı KOSGEB ve bankalar ile yapılacak protokollerle belirlenecektir.</p><p><a  href=\"https://www.resmigazete.gov.tr/eskiler/2020/04/20200403-10.pdf\" target=\"_blank\">https://www.resmigazete.gov.tr/eskiler/2020/04/20200403-10.pdf</a><br></p><div><br></div>\n                                <a target=\"_blank\" class=\"text-danger\" href=\"\">\n                                    \n                                </a>"}
