{"slug":"sirkuler-22-221-9548","reference":"Sirkuler_22_221","gazette":"OAİB","title":"İhracı kayda bağlı 4408 pozisyonundaki ürünler hk.","date":"22 Mart 2022","bodyHtml":"<p>Orta Anadolu İhracatçı Birlikleri tarafından yapılan duyuruya göre Tarım ve Orman Bakanlığı Orman Genel Müdürlüğü (OGM)’den gönderilen bir talimat ile 4408 tarife pozisyonundaki ürünlerin  ihracatının kayda alınması işlemleri 1 Haziran 2022 tarihi itibariyle başlayacaktır.</p><p> Kayıt işlemlerinin başlayacağı tarihe kadar standart ihracat prosedürü sürdürülecektir.</p><p>İlgili duyuru için <a  href=\"https://www.oaib.org.tr/tr/bulten-2022-3188.html\" target=\"_blank\" xss=removed>tıklayınız.</a></p>\n                                <a target=\"_blank\" class=\"text-danger\" href=\"\">\n                                    \n                                </a>"}
