{"slug":"sirkuler-25-0238","reference":"Sirkuler_25_0238","gazette":"EİB","title":"ABD Section 232 Önlemleri Kapsamında Yeni Türev Ürün Listeleri","date":"12 Mart 2025","bodyHtml":"<p>Ticaret Bakanlığı’ndan alınan bir yazıda, ABD Başkanı tarafından Section 232 önlemleri kapsamında ülke ve ürün bazında muafiyetlerin kaldırılması, alüminyum ürünlerinde uygulanan %10’luk ilave vergilerin %25’e yükseltilmesi ve önlemler kapsamına yeni türev ürünlerin eklenmesine ilişkin Başkanlık Kararlarıyla ilgili ABD Ticaret Bakanlığı tarafından hazırlanan Bildirimlerin 5 Mart 2025 tarihli ABD Resmi Gazetesi'nde yayımlandığı bildirilmektedir.</p><p>Yazının devamında, söz konusu Bildirimlerin incelenmesinden Section 232 önlemlerine tabi olacak yeni türev ürünlere ilişkin listelere, ilgili Bildirimlerin eklerinde yer verildiğinin görüldüğü bildirilmiş olup, bu kapsamda;</p><ul><li>Demir-çelik ürünlerine yönelik önlemler kapsamına, ABD gümrük tarife cetveline göre 167 adet yeni türev ürün eklendiği, söz konusu ürünlerin 155’inin, 73. fasılda yer almakta olduğu,</li><li>Geriye kalan ürünlerin elektrikli/elektriksiz makineler ve mobilya sektöründe bulunduğu,</li><li>Alüminyum ürünlerine yönelik önlemler kapsamına ise ABD gümrük tarife cetveline göre 123 adet yeni türev ürün eklendiği, söz konusu ürünlerin 19’unun 76. fasılda yer almakta olduğu, listenin, adi metallerden çeşitli eşya, elektrikli-elektriksiz makineler, otomotiv yan sanayi, hava taşıtlarının bazı aksam parçaları, silahlar için teleskopik dürbünler, oyuncaklar, oyun ve spor malzemeleri ile elektriksiz süpürge ve fırçalar gibi çeşitli sektör ve ürünü kapsamakta olduğu belirtilmektedir.</li></ul><p>Diğer taraftan yazıda, ilgili Başkanlık Kararları çerçevesinde türev ürünlerinde kullanılan demir-çeliğin veya alüminyumun ABD’de eritilip dökülmüş olması durumunda Section 232 önlemlerinin uygulanmayacağı, her iki Karar eki listelerde yer alan türev ürünlere yönelik %25’lik ilave verginin 12 Mart 2025 tarihi itibarıyla yürürlüğe gireceğinin hükme bağlandığı ifade edilmektedir. Söz konusu bildirimlere aşağıda yer alan bağlantı aracılığıyla ulaşılabilmektedir.</p><p><a href=\"https://eib.li/747B7\" target=\"_blank\" style=\"text-decoration-line: underline; font-weight: bold;\">Alüminyum İthalatına İlişkin Bildirim için tıklayınız.</a></p><p><a href=\"https://eib.li/574D5\" target=\"_blank\" style=\"text-decoration-line: underline; font-weight: bold;\">Demir Çelik İthalatına İlişkin Bildirim için tıklayınız.</a></p>\n                                <a target=\"_blank\" class=\"text-danger\" href=\"\">\n                                    \n                                </a>"}
