{"slug":"sirkuler-22-954-10301","reference":"Sirkuler_22_954","gazette":"İTKİB","title":"2015/2 sayılı Tekstil, Konfeksiyon, Deri ve Deri Ürünlerine İlişkin Dahilde İşleme Rejimi Genelgesinde Değişiklik Yapılmasına Dair Genelge Hakkında","date":"27 Aralık 2022","bodyHtml":"<p>06 Aralık 2022 tarihinde Ticaret Bakanlığı İhracat Genel Müdürlüğünden alınan yazıda;</p><p>2015/2 sayılı Tekstil, Konfeksiyon, Deri ve Deri Ürünlerine İlişkin Dahilde İşleme Rejimi Genelgesinde Değişiklik Yapılmasına Dair Genelge’nin yürürlüğe girdiği belirtilmekte olup, söz konusu değişiklikler aşağıda özetlenmektedir:<br></p><p>- <span xss=removed>Yan Sanayici Kapsamı Değişikliği</span>: Yurt içi yan sanayici protokolü ve yurt dışı sipariş sözleşmesi ibraz eden %1 indirimli teminat hakkına sahip firmalar, aynı üretim süreci için kendi kapasite raporunda yer alan üretim miktarı kadar üretimi (varsa vardiya yazısı da dikkate alınarak) yaptırmak için dahilde işleme izin belgesine yan sanayici ekleyebilir.<br></p><p>- <span xss=removed>Eşdeğer Eşya Değişikliği</span>:<br></p><p>1.1.2023’ten itibaren geçerli olacak şekilde, düzenlenecek dahilde işleme izin belgelerinin ithalat listesinde pamuk ipliği (GTİP: 5204, 5205, 5206, 5207), suni sentetik devamsız liflerden iplikler (GTİP: 5508, 5509, 5510, 5511), örme kumaş (Fasıl No:60) ve dokuma kumaş (GTİP: 5007, 5111, 5112, 5113, 5208, 5209, 5210, 5211, 5309, 5310, 5311, 5407, 5408, 5512, 5513, 5514, 5515, 5516) ürün gruplarının eşdeğer eşya olarak yer almasına izin verilmemesine karar verilmiştir.</p><p>Değişiklikleri yapan Genelge için<a  href=\"https://www.itkib.org.tr/files/downloads/Belgeler/2022/2015-2-Genelge.pdf\" target=\"_blank\" xss=removed> tıklayınız.</a></p>\n                                <a target=\"_blank\" class=\"text-danger\" href=\"\">\n                                    \n                                </a>"}
