{"slug":"sirkuler-10-170-5066","reference":"Sirkuler_10_170","gazette":"23.09.2010 tarih 27708 Resmi Gazete,","title":"-","date":"01 Ocak 2010","bodyHtml":"Sığır eti ithalatında Kontrol Belgesi alınabilmesi i&ccedil;in; Kontrol Belgesi başvurusu sırasında,&nbsp; 2000/32 sayılı Damızlık Harici Canlı Hayvanlar ile Hayvan Maddelerinin İthalatında Kontrol Belgesi D&uuml;zenlenmesi İ&ccedil;in Aranacak Belgeler Hakkında Tebliğde belirtilen evraklar ile birlikte diğer aranacak şartlar hk.\n                                <a target=\"_blank\" class=\"text-danger\" href=\"https://portal.ugm.com.tr/shared/DosyaAl.ashx?refno=REFSirkuler_10_170.zip&amp;arsivid=1874e3ad-256f-43ab-9a38-3155d3abe6d1\">\n                                    https://portal.ugm.com.tr/shared/DosyaAl.ashx?refno=REFSirkuler_10_170.zip&amp;arsivid=1874e3ad-256f-43ab-9a38-3155d3abe6d1\n                                </a>"}
