{"slug":"sirkuler-23-839-11299","reference":"Sirkuler_23_839","gazette":"EİB","title":"AB tarafından uygunsuz bulunan ihraç ürünlerimiz hk.","date":"23 Eylül 2023","bodyHtml":"<p xss=removed>Türkiye İhracatçılar Meclisi’nden iletilen bir yazıda, 7223 sayılı Ürün Güvenliği ve Teknik Düzenlemeler Kanunu’nun 12.03.2020 tarihli Resmî Gazete ’de yayımlanarak yürürlüğe girdiği ve ilgili Kanunun yürürlük tarihinden bu yana ihraç edilen ürünlerimizin uygun veya güvenli olmadığına ilişkin Ticaret Bakanlığına ulaşan iddiaların ihraç ürünlerimizin kalite ve güvenliğinin olumsuz yönde etkilenmemesi için incelendiği ve değerlendirildiği bildirilmektedir.</p><p xss=removed>Bahse konu yazıda devamla, Avrupa Komisyonu tarafından işletilen ve gıda dışı ürünler için kullanılan Avrupa Birliği Hızlı Uyarı Sistemi (RAPEX) aracılığıyla, Avrupa Ekonomik Alanı ülkeleri ile Komisyon arasında “AB piyasasına gönderilen ve insan sağlığı ile güvenliğine karşı risk oluşturan ürünlere” yönelik bilgi paylaşımının sağlandığı belirtilmektedir. Bu kapsamda, kimyevi maddeler ve mamulleri, hazır giyim ve konfeksiyon ile mobilya, kâğıt ve orman ürünleri sektörleri başta olmak üzere ülkemizden AB’ye ihraç edilen ve RAPEX üzerinde Nisan 2021-Ağustos 2023 dönemi için yayınlanan ürünler ekli tabloda listelenmektedir.</p><p xss=removed> <a  href=\"https://upload.eib.org.tr/UyeDuyuruSistemiEkler/2023/9/6872175152023922162533/Nisan 2021-Ağustos 2023 RAPEX Bildirimleri_3E456.pdf\" target=\"_blank\" xss=removed>Nisan 2021-Ağustos 2023 dönemi için duyurulan uygunsuz ürünler için tıklayınız</a>.<br></p>\n                                <a target=\"_blank\" class=\"text-danger\" href=\"\">\n                                    \n                                </a>"}
