{"slug":"sirkuler-11-172-4844","reference":"Sirkuler_11_172","gazette":"02.08.2011 tarih 28013 sayılı Resmi Gazete,","title":"-","date":"01 Ocak 2011","bodyHtml":"<p>\n\t<strong>A - Konu : </strong>19/7/2009 tarihli ve 27293 sayılı Resm&icirc; Gazete&rsquo;de yayımlanan Batı Balkan Menşe K&uuml;m&uuml;lasyon Sistemi Kapsamı Ticarette Eşyanın Tercihli Menşeinin Tespiti Hakkında Y&ouml;netmelikte Değişiklik yapıldığı hk.<br />\n\t<strong>B - Konu :</strong> 19/7/2009 tarihli ve 27293 sayılı Resm&icirc; Gazete&rsquo;de yayımlanan İki Taraflı Menşe K&uuml;m&uuml;lasyon Sistemi Kapsamı Ticarette Eşyanın Tercihli Menşeinin Tespiti Hakkında Y&ouml;netmelikte Değişiklik yapıldığı hk.</p>\n\n                                <a target=\"_blank\" class=\"text-danger\" href=\"https://portal.ugm.com.tr/shared/DosyaAl.ashx?refno=REFSirkuler_11_172.zip&amp;arsivid=3b680eb5-74bd-4a4b-8c7d-f160968dde1c\">\n                                    https://portal.ugm.com.tr/shared/DosyaAl.ashx?refno=REFSirkuler_11_172.zip&amp;arsivid=3b680eb5-74bd-4a4b-8c7d-f160968dde1c\n                                </a>"}
