{"slug":"sirkuler-25-0384","reference":"Sirkuler_25_0384","gazette":"İGMD","title":"İhracat Sonrası Süresi İçinde Geri Gelen Eşyanın Gümrükleme Sürecinde Yaşanan Sorunlar hk.","date":"06 Mayıs 2025","bodyHtml":"<p>Gümrük Müşavirleri Derneklerince;</p><p>-ihraç edildikten sonra çeşitli nedenlerle geri gelen eşyanın kullanılmış olarak beyan edilmesi durumunda gümrük idarelerinde farklı uygulamalar yapıldığı,</p><p>-eşyanın ilk kullanım dışında kullanılıp kullanılmadığının tespiti için üniversitelere gönderildiği ve bu durumun firmalar açısından yüksek ·maliyetlere sebep olduğu </p><p>belirtilerek&nbsp; Gümrük Kanununun 168 inci maddesi ve 2013/33 sayılı Genelge çerçevesinde yeknesak bir uygulama yapılması <a href=\"https://files.igmd.org.tr/doc/6052025-095658_2025-1123-bupdf.pdf\" target=\"_blank\" style=\"text-decoration-line: underline; font-weight: bold;\">talep edilmişti.</a></p><p>Gümrükler Genel Müdürlüğü'nün <a href=\"https://files.igmd.org.tr/doc/6052025-095734_cevabi-yazipdf.pdf\" target=\"_blank\" style=\"text-decoration-line: underline; font-weight: bold;\">cevabi yazısında</a>; Kanunun 168 inci maddesi kapsamında geri gelen eşya olarak beyan edilen eşya için gümrük idaresince yukarıda belirtilen mevzuat hükümleri uyarınca işlem yapılması dolayısıyla eşyanın ilk kullanım dışında kullanılıp kullanılmadığına ilişkin tespitin yapılmasının gerektiği ve bu tespitin gümrük idaresince yapılamaması halinde eşyanın sanayi odası, üniversite gibi uzman bir kuruluşa yönlendirilerek buradan alınacak rapor doğrultusunda işlemlerin tamamlanması gerektiği belirtildi.</p><p><br></p>\n                                <a target=\"_blank\" class=\"text-danger\" href=\"\">\n                                    \n                                </a>"}
