{"slug":"sirkuler-21-499-8884","reference":"Sirkuler_21_499","gazette":"DMO","title":"Kişisel koruyucu donanım ürünleri ihracatında hibe uygulaması hk.16 Temmuz itibariyle kaldırıldı","date":"09 Temmuz 2021","bodyHtml":"<p xss=removed>Kişisel koruyucu donanım ürünleri ihracatında hibe uygulaması 16 Temmuz itibariyle kaldırıldı.</p><p xss=removed>Devlet Malzeme Ofisi (DMO) internet sitesinde yapılan duyuruda;</p><p xss=removed>Koronavirüs (COVID-19) salgını kapsamında kamu kurum ve kuruluşlarının ihtiyaç duydukları kişisel koruyucu donanım ürünleri taleplerinin tedarik edilmesi ve bunların dağıtımının sağlanması konularında Genel Müdürlüklerinin görevlendirildiği bilgisi verilerek;<br></p><p xss=removed>Tedarikçilerle hibe-ihracat modeli kapsamında mal alım sözleşmeleri imzalamak suretiyle kamu kurum ve kuruluşlarının ihtiyaç duydukları “Cerrahi Maske, FFP2 (N95) / FFP3 Maske, Koruyucu Tulum, Sıvı Geçirmez Kişisel Koruyucu Önlük, Koruyucu Gözlük, Nonsteril Nitril Tıbbi Muayene Eldiveni, Nonsteril Pudralı Tıbbi Muayene Eldiveni, Nonsteril Pudrasız Tıbbi Muayene Eldiveni, Lateks İçermeyen, Pudrasız Cerrahi Eldiveni, Lateks İçeren, Pudralı Cerrahi Eldiveni, Lateks İçeren, Pudrasız Cerrahi Eldiven” taleplerinin tedarik edilmesi ve dağıtımının Genel Müdürlüklerince yürütüldüğü belirtilmektedir.<br></p><p xss=removed>Duyuruda, pandemi sürecinin başlangıcından bugüne kadar salgının kontrol altına alınabilmesi için ülke genelinde yürürlükte olan kısıtlama döneminde uygulanan hibe-ihracat modeli ile kamu kurum kuruluşlarının kişisel koruyucu donanım ürünleri ihtiyacı tedarik edilmiş olup gelinen aşamada salgının kontrol altına alınması, kişisel koruyucu donanım tedarikinde arz güvenliğinin sağlanması, 21.06.2021 tarihinde toplanan Cumhurbaşkanlığı kabinesinde kademeli normalleşme sürecinin 3’üncü etabına geçilmesi ve 01.07.2021 tarihi itibarıyla kısıtlamaların kaldırılması ile birlikte Genel Müdürlüklerince yürütülen hibe ihracat uygulamasının ve TİTCK ile imzalanmış olan “İhracı Yasak ve Ön İzne Bağlı Mallara İlişkin Tebliğ (İhracat: 96/31) Uyarınca Verilecek İhracat Ön izinlerine İlişkin Protokol” ün 16.07.2021 tarihi itibari ile sonlandırılmasına karar verildiği ifade edilmektedir.</p><p>İlgili duyuru için  <a  href=\"https://www.dmo.gov.tr/Home/Icerik/3676\" target=\"_blank\" xss=removed>tıklayınız.</a></p>\n                                <a target=\"_blank\" class=\"text-danger\" href=\"http://portal.ugm.com.tr/shared/dosyaal.ashx?arsivid=21468dd3-59fd-4adb-8c28-61e3729d2a5c&amp;refno=REF2021_499.rar\">\n                                    http://portal.ugm.com.tr/shared/dosyaal.ashx?arsivid=21468dd3-59fd-4adb-8c28-61e3729d2a5c&amp;refno=REF2021_499.rar\n                                </a>"}
