{"slug":"sirkuler-21-731-9141","reference":"Sirkuler_21_731","gazette":"05 Kasım 2021 Tarihli ve 31650 Sayılı Resmî Gazete","title":"Almanya, İspanya ve İtalya menşeli/çıkışlı kumaşlarda Üretici Belgesi ibrazı hk.","date":"05 Kasım 2021","bodyHtml":"<p>5407, 55.13, 55.14,55.15, 55.16 tarife pozisyonlarında bulunan mensucatın Almanya, İspanya ve İtalya menşeli/çıkışlı olanlarının ithalatında ihracatçı firma bazında İthalatta Haksız Rekabetin Önlenmesine İlişkin Tebliğ (Tebliğ No: 2021/41)le belirlenen oranlarda dampinge karşı vergi tahsil edilmekte. Tebliğde belirtilenlerin dışındaki firmalar (diğerleri) için belirlenen %0 oranının uygulanmasını isteyen firmaların Üretici belgesi ibraz etmesi gerekecek.</p><p>Konuya ilişkin Tebliğ değişikliği için <a  href=\"https://www.resmigazete.gov.tr/eskiler/2021/11/20211105-11.htm\" target=\"_blank\" xss=removed>tıklayınız.</a></p>\n                                <a target=\"_blank\" class=\"text-danger\" href=\"\">\n                                    \n                                </a>"}
