{"slug":"sirkuler-24-0397eng","reference":"Sirkuler_24_0397ENG","gazette":"the Official Gazette, nr.32545, dated 13th of May .","title":"The list of goods within the scope of the agreement between Turkey and Qatar has been expanded","date":"14 Mayıs 2024","bodyHtml":"<p>On May 13, 2024, the decision regarding the approval of the notes amending the Trade and Economic Partnership Agreement between the Government of the Republic of Turkey and the Government of the State of Qatar (Decision Number: 8448) was published in the Official Gazette, numbered 32545, and published in the first repeat.</p><p>With this decision, the list of goods within the scope of the agreement between Turkey and Qatar was expanded in accordance with the mutual notes exchanged in 2023.<br></p><p>Upon the entry into force of the agreement, customs duties will be zeroed for the goods listed in the relevant appendices.<br></p><p>The preferential origin of the goods covered by the agreement will be proven with an EUR.1 Movement Certificate or an invoice declaration (which can be made by an Approved Exporter for amounts over 6000 EUR).<br></p><p>The lists of goods for which both countries grant tax concessions and rules of origin can be checked from the following page ranges:<br></p><p>-List of goods for which import duties are zeroed in Turkey (pp.1135-1280 and 1407-1444)<br></p><p>-List of goods for which import duties are zeroed in Qatar (pp. 1281-1313 and 1445-1516).</p><p>Additionally, the protocol of origin (pp. 1042-1073) and rules of origin (pp.1074-1128) are available.</p><p><a href=\"https://www.resmigazete.gov.tr/eskiler/2024/05/20240513M1-1.pdf\" target=\"_blank\" style=\"text-decoration-line: underline; font-weight: bold;\">Click here for the Decision regarding the Approval of the Notes Amending the Trade and Economic Partnership Agreement between the Government of the Republic of Turkey and the Government of the State of Qatar (Decision Number: 8448).</a><br></p>\n                                <a target=\"_blank\" class=\"text-danger\" href=\"\">\n                                    \n                                </a>"}
