{"slug":"sirkuler-12-196-4518","reference":"Sirkuler_12_196","gazette":"19.07.2012 Tarihli, 28358 Sayılı Resmi Gazete,","title":"İthalatta Korunma Önlemlerine İlişkin Tebliğ (2012-14) hk. (Plastik sanayi dikkatine)","date":"19 Temmuz 2012","bodyHtml":"<p style=\"text-align: justify;\">\n\t3901.10.90.00.11 G&uuml;mr&uuml;k Tarife İstatistik Pozisyonlu (Al&ccedil;ak Yoğunluk Polietilen) isimli eşyanın İran menşeli olanlarının ithalatında &uuml;&ccedil; yıl s&uuml;reyle korunma &ouml;nlemi uygulanmasına, &ouml;nlemin anılan &uuml;lke menşeli ithalatta tahsil edilecek ek mali y&uuml;k&uuml;ml&uuml;l&uuml;k şeklinde belirlenmesine, ek mali y&uuml;k&uuml;ml&uuml;l&uuml;ğ&uuml;n tabloda g&ouml;sterildiği şekilde tespit edilmesine ve &ouml;nlemin istihsali hususunda Bakanlar Kuruluna &ouml;neride bulunulmasına karar verildiği hk.<br />\n\t&nbsp;</p>\n\n                                <a target=\"_blank\" class=\"text-danger\" href=\"https://portal.ugm.com.tr/shared/DosyaAl.ashx?refno=REFsirkuler_12_07190926.zip&amp;arsivid=a4a5183b-6eec-41a9-9f0e-7093eb1544df\">\n                                    https://portal.ugm.com.tr/shared/DosyaAl.ashx?refno=REFsirkuler_12_07190926.zip&amp;arsivid=a4a5183b-6eec-41a9-9f0e-7093eb1544df\n                                </a>"}
