{"slug":"sirkuler-20-462-7716","reference":"Sirkuler_20_462","gazette":"OAİB","title":"Birleşik Krallık Gümrük Vergileri Uygulaması ve Kuru meyve ürünleri","date":"28 Mayıs 2020","bodyHtml":"<p xss=removed>Birleşik Krallık Hükümeti  19 Mayıs 2020 tarihinde Birleşik Krallık Global Tarife Rejimi (UKGT) uygulamasını açıkladı ve anılan uygulamanın 1 Ocak 2021 tarihi itibariyle Avrupa Birliği Ortak Gümrük Tarifesi (CET) uygulamasının yerine geçeceği belirtti.</p><p xss=removed>Bu kapsamda, kuru meyve sektöründe ülkemiz için en önemli dış piyasalardan bir tanesini teşkil eden Birleşik Krallık tarafından, anılan uygulama hayata geçtiği gün itibarıyla ülkemiz menşeli bazı kuru meyve ürünlerine aşağıdaki şekilde gümrük vergisi uygulanacağı anlaşılmaktadır.</p><p xss=removed>-Çekirdeksiz kuru üzüm % 2</p><p xss=removed>-Kuru incir % 8</p><p xss=removed>-Kuru kayısı % 4</p><p xss=removed>Konuya için açıklama için <a  href=\"http://www.oaib.gov.tr/tr/sirkuler-2020-6211.pdf\" target=\"_blank\">tıklayınız.</a></p><div xss=removed><br></div>\n                                <a target=\"_blank\" class=\"text-danger\" href=\"\">\n                                    \n                                </a>"}
