{"slug":"sirkuler-22-055-9367","reference":"Sirkuler_22_055","gazette":"GGM","title":"Tıbbi Amaçlı Olan Mamalar ve Enteral Beslenme Ürünlerinde ÖTV hk.","date":"11 Ocak 2022","bodyHtml":"<p>2022 yılı tarife cetvelinde 2202.99 tarife alt pozisyonlarında sınıflandırılan sıvı haldeki \"yalnız tıbbi amaçlı olan mamalar ve enteral beslenme ürünleri\" nin ÖTV (III) Sayılı liste kapsamında ÖTV'ye tabi olmadığına ilişkin bir yazı yayımlandı.</p><p>İlgili yazı eklidir.</p>\n                                <a target=\"_blank\" class=\"text-danger\" href=\"http://portal.ugm.com.tr/shared/dosyaal.ashx?arsivid=fe025487-b315-4062-b932-75097d0484df&amp;refno=REF2022_055.rar\">\n                                    http://portal.ugm.com.tr/shared/dosyaal.ashx?arsivid=fe025487-b315-4062-b932-75097d0484df&amp;refno=REF2022_055.rar\n                                </a>"}
