{"slug":"sirkuler-23-107-10442","reference":"Sirkuler_23_107","gazette":"25 Ocak 2023 Tarihli ve 32084 Sayılı Resmî Gazete","title":"Bulgaristan, Fransa ve Kuzey Makedonya menşeli/çıkışlı deri taklidi mensucat için soruşturma açıldı","date":"25 Ocak 2023","bodyHtml":"<p>Bulgaristan, Fransa ve Kuzey Makedonya menşeli/çıkışlı 5903.20 GTP altında kayıtlı “mensucat, poliüretanla emdirilmiş, sıvanmış, kaplanmış veya lamine edilmiş-deri taklidi/diğerleri” ithalatına ilişkin olarak  dampinge karşı önlemlerin etkisiz kılınmasına karşı soruşturma açılmasına karar verildi.</p><p>Bulgaristan, Fransa ve Kuzey Makedonya menşeli/çıkışlı 5903.20 GTP altında kayıtlı “mensucat, poliüretanla emdirilmiş, sıvanmış, kaplanmış veya lamine edilmiş-deri taklidi/diğerleri” ithalatında İthalatta Haksız Rekabetin Önlenmesine İlişkin Tebliğ (Tebliğ No: 2016/44) çerçevesinde ÇHC menşeli ithalatta uygulanan dampinge karşı önlemle aynı tutarlarda   (  5903.20.10 için 1  ABD Doları/kg ; 5903.20.90 için 2,2 ABD Doları/kg) teminat alınacak.</p><p><a  href=\"https://www.resmigazete.gov.tr/eskiler/2023/01/20230125-3.htm\" target=\"_blank\" xss=removed>İthalatta Haksız Rekabetin Önlenmesine İlişkin Tebliğ (No: 2023/4)</a><br></p><p><br></p><p><br></p>\n                                <a target=\"_blank\" class=\"text-danger\" href=\"\">\n                                    \n                                </a>"}
