{"slug":"sirkuler-21-606-9001","reference":"Sirkuler_21_606","gazette":"EİB","title":"531 sıra numaralı Vergi Usul Kanunu Genel Tebliği ( akaryakıt, madeni yağ, tütün, alkollü içecek sektörü)","date":"06 Eylül 2021","bodyHtml":"<p>2 Eylül 2021 tarihli Resmi Gazete’de yayımlanan 531 sıra numaralı Vergi Usul Kanunu Genel Tebliği ile akaryakıt, madeni yağ, tütün, alkollü içecek sektöründe faaliyet gösteren mükelleflerde belge düzeni ve teminat uygulamasına ilişkin düzenlemeye gidilmiştir.</p><p>Konuya ilişkin Ege İhracatçılar Birliği tarafından hazırlanan Bilgi Notu için <a  href=\"https://upload.eib.org.tr/ZZFAF3F52D/9C767E1AB267419C767E1AB267419C767E1AB267419C767E1A.pdf\" target=\"_blank\" xss=removed>tıklayınız.</a></p><p><br></p><p><br></p>\n                                <a target=\"_blank\" class=\"text-danger\" href=\"\">\n                                    \n                                </a>"}
